piwrapper/PiConnect.py
piwrapper/PiConsts.py
piwrapper/__init__.py
piwrapper-0.3.0.dist-info/LICENSE
piwrapper-0.3.0.dist-info/METADATA
piwrapper-0.3.0.dist-info/WHEEL
piwrapper-0.3.0.dist-info/top_level.txt
piwrapper-0.3.0.dist-info/RECORD
