Metadata-Version: 2.1
Name: piwrapper
Version: 0.3.0
Summary: Python connector access OSISOFT PI server via PI Web API.
Home-page: https://github.com/joshylchen/piwrapper
Author: Josh Chen
Author-email: jcpythonlib@gmail.com
License: MIT
Platform: UNKNOWN
Classifier: Development Status :: 2 - Pre-Alpha
Classifier: License :: OSI Approved :: MIT License
Classifier: Programming Language :: Python
Classifier: Programming Language :: Python :: 3.6
Classifier: Programming Language :: Python :: 3.7
Classifier: Programming Language :: Python :: 3.8
Classifier: Programming Language :: Python :: 3.9
Requires-Python: >=3.6.0
License-File: LICENSE
Requires-Dist: numpy (>=1.21.3)
Requires-Dist: pandas (>=1.3.4)
Requires-Dist: python-dateutil (>=2.8)
Requires-Dist: requests (>=2.26)
Requires-Dist: requests-kerberos (>=0.12)
Requires-Dist: tqdm (>=4.32)
Requires-Dist: tzlocal (>=1.5)
Requires-Dist: urllib3 (>=1.26.7)
